time_server_mcp/__init__.py
time_server_mcp/timeserver2.py
time_server_mcp_ver_pcc-0.1.1.dist-info/METADATA
time_server_mcp_ver_pcc-0.1.1.dist-info/WHEEL
time_server_mcp_ver_pcc-0.1.1.dist-info/entry_points.txt
time_server_mcp_ver_pcc-0.1.1.dist-info/top_level.txt
time_server_mcp_ver_pcc-0.1.1.dist-info/RECORD
